fcgi_pando.py
pando/__init__.py
pando/__main__.py
pando/body_parsers.py
pando/exceptions.py
pando/logging.py
pando/state_chain.py
pando/urlparse.py
pando/utils.py
pando/website.py
pando/wsgi.py
pando/auth/__init__.py
pando/auth/cookie.py
pando/auth/httpbasic.py
pando/http/__init__.py
pando/http/baseheaders.py
pando/http/mapping.py
pando/http/request.py
pando/http/response.py
pando/testing/__init__.py
pando/testing/client.py
pando/testing/harness.py
pando/www/autoindex.html.spt
pando/www/error.spt
pando/www/favicon.ico
pando-0.47.dist-info/METADATA
pando-0.47.dist-info/WHEEL
pando-0.47.dist-info/entry_points.txt
pando-0.47.dist-info/top_level.txt
pando-0.47.dist-info/RECORD
