Metadata-Version: 2.1
Name: pando
Version: 0.47
Summary: Pando is a Python web framework. Simplates are the main attraction.
Home-page: http://aspen.io/
Author: Chad Whitacre et al.
Author-email: team@aspen.io
License: UNKNOWN
Platform: UNKNOWN
Classifier: Development Status :: 4 - Beta
Classifier: Environment :: Console
Classifier: Intended Audience :: Developers
Classifier: License :: OSI Approved :: MIT License
Classifier: Natural Language :: English
Classifier: Operating System :: OS Independent
Classifier: Programming Language :: Python :: 2.7
Classifier: Programming Language :: Python :: 3.4
Classifier: Programming Language :: Python :: 3.5
Classifier: Programming Language :: Python :: 3.6
Classifier: Programming Language :: Python :: 3.7
Classifier: Programming Language :: Python :: Implementation :: CPython
Classifier: Topic :: Internet :: WWW/HTTP :: WSGI :: Application
Requires-Dist: python-mimeparse (>=0.1.4)
Requires-Dist: first (>=2.0.1)
Requires-Dist: state-chain (>=1.3.0)
Requires-Dist: filesystem-tree (>=1.0.1)
Requires-Dist: dependency-injection (>=1.2.0)
Requires-Dist: aspen (==1.0rc7)
Requires-Dist: six
Provides-Extra: fcgi
Requires-Dist: flup ; extra == 'fcgi'
